{"data":{"allMarkdownRemark":{"totalCount":2,"edges":[{"node":{"id":"5717f9e4-9c22-5911-aabc-80da104ca69d","frontmatter":{"title":"About Gatsby","date":"October 10, 2018","path":"/contents/gatsby","categories":["gatsby","react"],"tags":["gatsby","react","typescript","graphql"],"excerpt":"Gatsby Sample Page"}}},{"node":{"id":"f0fcc98b-4a32-5d09-ac57-c12d6358eabc","frontmatter":{"title":"About Markdown","date":"October 10, 2018","path":"/contents/markdown","categories":["markdown"],"tags":["markdown"],"excerpt":"About Markdown"}}}]}},"pageContext":{}}